scholar_author_scraper/__init__.py
scholar_author_scraper/scholar_author_scraper.py
tests/__init__.py
tests/test_app.py
researcher_papers-0.1.0.dist-info/METADATA
researcher_papers-0.1.0.dist-info/WHEEL
researcher_papers-0.1.0.dist-info/entry_points.txt
researcher_papers-0.1.0.dist-info/top_level.txt
researcher_papers-0.1.0.dist-info/RECORD
